simplify/__init__.py
simplify/fuse.py
simplify/layers.py
simplify/propagate.py
simplify/remove.py
simplify/utils.py
test/__init__.py
test/utils.py
test/modules/__init__.py
test/modules/fuse.py
test/modules/propagate.py
test/modules/remove.py
torch_simplify-1.1.4.dist-info/LICENSE
torch_simplify-1.1.4.dist-info/METADATA
torch_simplify-1.1.4.dist-info/WHEEL
torch_simplify-1.1.4.dist-info/top_level.txt
torch_simplify-1.1.4.dist-info/RECORD
