Metadata-Version: 2.1
Name: torch-simplify
Version: 1.1.4
Summary: Simplification of pruned models for accelerated inference
Home-page: https://github.com/EIDOSlab/simplify
Author: EIDOSlab
Author-email: eidoslab@di.unito.it
License: BSD 3-Clause
Requires-Python: >=3.6
License-File: LICENSE
Requires-Dist: torch
Requires-Dist: torchvision
